neuraltrack/__init__.py
neuraltrack/logging/__init__.py
neuraltrack/logging/gradient_logger.py
neuraltrack/logging/loss_logger.py
neuraltrack/utils/__init__.py
neuraltrack/visualization/__init__.py
neuraltrack/visualization/gradient_plot.py
neuraltrack/visualization/loss_plot.py
neuraltrack-1.0.1.dist-info/LICENSE
neuraltrack-1.0.1.dist-info/METADATA
neuraltrack-1.0.1.dist-info/WHEEL
neuraltrack-1.0.1.dist-info/entry_points.txt
neuraltrack-1.0.1.dist-info/top_level.txt
neuraltrack-1.0.1.dist-info/RECORD
