Metadata-Version: 2.2
Name: neuraltrack
Version: 1.0.1
Summary: NeuralTrack is a lightweight logging tool for deep learning training
Home-page: https://github.com/sciencehope/NeuralTrack
Author: Science Hope
Author-email: 
License: MIT
Classifier: Programming Language :: Python :: 3
Classifier: License :: OSI Approved :: MIT License
Classifier: Operating System :: OS Independent
Requires-Python: >=3.6
License-File: LICENSE
Requires-Dist: numpy
Requires-Dist: matplotlib
Dynamic: author
Dynamic: classifier
Dynamic: description
Dynamic: description-content-type
Dynamic: home-page
Dynamic: license
Dynamic: requires-dist
Dynamic: requires-python
Dynamic: summary
